Metadata-Version: 1.0
Name: smn20-dist-probability
Version: 0.1
Summary: Gaussian and Binomial distributions
Home-page: UNKNOWN
Author: smn20
Author-email: UNKNOWN
License: UNKNOWN
Platform: UNKNOWN
